{
  "activities": [
    {
      "id": "paris-mus-001",
      "city": "Paris",
      "country": "France",
      "name": "Mus\u00e9e d'Orsay",
      "category": "museum",
      "description": "World-class Impressionist and Post-Impressionist art in a stunning Beaux-Arts railway station.",
      "lat": 48.8599,
      "lon": 2.3266,
      "neighborhood": "7th arrondissement",
      "tags": [
        "museums",
        "art",
        "indoor",
        "touristy",
        "history"
      ]
    },
    {
      "id": "paris-mus-002",
      "city": "Paris",
      "country": "France",
      "name": "Centre Pompidou",
      "category": "museum",
      "description": "Modern and contemporary art with iconic inside-out architecture and rooftop city views.",
      "lat": 48.8606,
      "lon": 2.3522,
      "neighborhood": "Beaubourg",
      "tags": [
        "museums",
        "architecture",
        "indoor",
        "touristy"
      ]
    },
    {
      "id": "paris-food-001",
      "city": "Paris",
      "country": "France",
      "name": "March\u00e9 Bastille",
      "category": "food_market",
      "description": "Large Sunday market popular with locals for produce, cheese, and street food.",
      "lat": 48.8531,
      "lon": 2.3691,
      "neighborhood": "Bastille",
      "tags": [
        "food",
        "local",
        "shopping",
        "outdoor"
      ]
    },
    {
      "id": "paris-food-002",
      "city": "Paris",
      "country": "France",
      "name": "Bistrot Paul Bert",
      "category": "restaurant",
      "description": "Classic Parisian bistro experience with steak frites and wine \u2014 busy and beloved.",
      "lat": 48.8536,
      "lon": 2.3844,
      "neighborhood": "11th arrondissement",
      "tags": [
        "food",
        "local",
        "nightlife"
      ]
    },
    {
      "id": "paris-nat-001",
      "city": "Paris",
      "country": "France",
      "name": "Promenade Plant\u00e9e / Coul\u00e9e Verte",
      "category": "park",
      "description": "Elevated linear park perfect for a relaxed walk away from car traffic.",
      "lat": 48.8488,
      "lon": 2.3704,
      "neighborhood": "12th arrondissement",
      "tags": [
        "nature",
        "local",
        "outdoor",
        "wellness"
      ]
    },
    {
      "id": "paris-night-001",
      "city": "Paris",
      "country": "France",
      "name": "Jazz Club Caveau de la Huchette",
      "category": "nightlife",
      "description": "Historic cellar jazz club with dancing; late nights and lively crowds.",
      "lat": 48.8522,
      "lon": 2.3455,
      "neighborhood": "Latin Quarter",
      "tags": [
        "nightlife",
        "music",
        "touristy",
        "indoor"
      ]
    },
    {
      "id": "paris-shop-001",
      "city": "Paris",
      "country": "France",
      "name": "Le Marais boutiques",
      "category": "shopping",
      "description": "Independent fashion and design shops mixed with caf\u00e9s in a walkable historic quarter.",
      "lat": 48.8556,
      "lon": 2.3655,
      "neighborhood": "Le Marais",
      "tags": [
        "shopping",
        "local",
        "architecture",
        "food"
      ]
    },
    {
      "id": "paris-hist-001",
      "city": "Paris",
      "country": "France",
      "name": "Sainte-Chapelle",
      "category": "attraction",
      "description": "Gothic chapel famous for stained-glass windows; compact visit, strong visual payoff.",
      "lat": 48.8556,
      "lon": 2.3451,
      "neighborhood": "\u00cele de la Cit\u00e9",
      "tags": [
        "history",
        "architecture",
        "touristy",
        "indoor"
      ]
    },
    {
      "id": "paris-ev-001",
      "city": "Paris",
      "country": "France",
      "name": "Seine evening river cruise",
      "category": "tour",
      "description": "Sightseeing boat tour past illuminated monuments; classic tourist experience.",
      "lat": 48.8606,
      "lon": 2.2932,
      "neighborhood": "Champ de Mars",
      "tags": [
        "touristy",
        "nightlife",
        "history",
        "outdoor"
      ]
    },
    {
      "id": "tokyo-mus-001",
      "city": "Tokyo",
      "country": "Japan",
      "name": "TeamLab Planets",
      "category": "museum",
      "description": "Immersive digital art museum where visitors wade through installations.",
      "lat": 35.6491,
      "lon": 139.7899,
      "neighborhood": "Toyosu",
      "tags": [
        "museums",
        "art",
        "indoor",
        "touristy"
      ]
    },
    {
      "id": "tokyo-food-001",
      "city": "Tokyo",
      "country": "Japan",
      "name": "Tsukiji Outer Market",
      "category": "food_market",
      "description": "Street food, seafood snacks, and kitchenware; early morning energy.",
      "lat": 35.6654,
      "lon": 139.7707,
      "neighborhood": "Tsukiji",
      "tags": [
        "food",
        "local",
        "shopping",
        "touristy"
      ]
    },
    {
      "id": "tokyo-nat-001",
      "city": "Tokyo",
      "country": "Japan",
      "name": "Shinjuku Gyoen National Garden",
      "category": "park",
      "description": "Spacious garden mixing French, English, and Japanese landscape styles.",
      "lat": 35.6852,
      "lon": 139.71,
      "neighborhood": "Shinjuku",
      "tags": [
        "nature",
        "wellness",
        "outdoor",
        "local"
      ]
    },
    {
      "id": "tokyo-night-001",
      "city": "Tokyo",
      "country": "Japan",
      "name": "Golden Gai",
      "category": "nightlife",
      "description": "Tiny bars in narrow alleys; intimate nightlife scene with local regulars.",
      "lat": 35.6944,
      "lon": 139.7048,
      "neighborhood": "Shinjuku",
      "tags": [
        "nightlife",
        "local",
        "food",
        "music"
      ]
    },
    {
      "id": "tokyo-hist-001",
      "city": "Tokyo",
      "country": "Japan",
      "name": "Senso-ji Temple",
      "category": "attraction",
      "description": "Tokyo's oldest temple with a bustling traditional shopping street approach.",
      "lat": 35.7148,
      "lon": 139.7967,
      "neighborhood": "Asakusa",
      "tags": [
        "history",
        "architecture",
        "touristy",
        "shopping"
      ]
    },
    {
      "id": "tokyo-shop-001",
      "city": "Tokyo",
      "country": "Japan",
      "name": "Shibuya Parco & surrounding",
      "category": "shopping",
      "description": "Trendy retail, indie labels, and pop-culture floors near the famous crossing.",
      "lat": 35.6622,
      "lon": 139.6982,
      "neighborhood": "Shibuya",
      "tags": [
        "shopping",
        "touristy",
        "food",
        "music"
      ]
    },
    {
      "id": "tokyo-sp-001",
      "city": "Tokyo",
      "country": "Japan",
      "name": "Local sento (public bath) evening",
      "category": "wellness",
      "description": "Neighborhood bathhouse ritual \u2014 low-key, authentic, and restorative after walking.",
      "lat": 35.708,
      "lon": 139.752,
      "neighborhood": "Shinagawa",
      "tags": [
        "wellness",
        "local",
        "nightlife"
      ]
    },
    {
      "id": "bcn-mus-001",
      "city": "Barcelona",
      "country": "Spain",
      "name": "Museu Picasso",
      "category": "museum",
      "description": "Extensive Picasso collection focused on early works in medieval palaces.",
      "lat": 41.3853,
      "lon": 2.1809,
      "neighborhood": "El Born",
      "tags": [
        "museums",
        "art",
        "history",
        "touristy",
        "indoor"
      ]
    },
    {
      "id": "bcn-arch-001",
      "city": "Barcelona",
      "country": "Spain",
      "name": "Sagrada Fam\u00edlia exterior walk",
      "category": "attraction",
      "description": "Gaud\u00ed's basilica \u2014 even viewing from the park offers strong architecture payoff.",
      "lat": 41.4036,
      "lon": 2.1744,
      "neighborhood": "Eixample",
      "tags": [
        "architecture",
        "touristy",
        "outdoor",
        "history"
      ]
    },
    {
      "id": "bcn-food-001",
      "city": "Barcelona",
      "country": "Spain",
      "name": "Mercat de Sant Antoni",
      "category": "food_market",
      "description": "Local market with tapas bars \u2014 less packed than Boqueria for a neighborhood feel.",
      "lat": 41.3786,
      "lon": 2.1622,
      "neighborhood": "Sant Antoni",
      "tags": [
        "food",
        "local",
        "shopping"
      ]
    },
    {
      "id": "bcn-food-002",
      "city": "Barcelona",
      "country": "Spain",
      "name": "Vermut hour in Gr\u00e0cia",
      "category": "food_experience",
      "description": "Pre-lunch vermouth and olives at a terrace bar in a village-like district.",
      "lat": 41.402,
      "lon": 2.1566,
      "neighborhood": "Gr\u00e0cia",
      "tags": [
        "food",
        "local",
        "nightlife"
      ]
    },
    {
      "id": "bcn-nat-001",
      "city": "Barcelona",
      "country": "Spain",
      "name": "Park G\u00fcell viewpoints",
      "category": "park",
      "description": "Gaud\u00ed park with mosaic terraces; nature views over the city (ticketed zones vary).",
      "lat": 41.4145,
      "lon": 2.1527,
      "neighborhood": "Gr\u00e0cia",
      "tags": [
        "nature",
        "architecture",
        "touristy",
        "outdoor"
      ]
    },
    {
      "id": "bcn-night-001",
      "city": "Barcelona",
      "country": "Spain",
      "name": "Poble-sec tapas crawl",
      "category": "nightlife",
      "description": "Carrer de Blai pincho bars \u2014 casual late evening food and drinks.",
      "lat": 41.3729,
      "lon": 2.1611,
      "neighborhood": "Poble-sec",
      "tags": [
        "nightlife",
        "food",
        "local"
      ]
    },
    {
      "id": "bcn-beach-001",
      "city": "Barcelona",
      "country": "Spain",
      "name": "Barceloneta beach stroll",
      "category": "outdoor",
      "description": "Sea breeze walk; can be touristy midday but pleasant at sunset.",
      "lat": 41.3784,
      "lon": 2.1925,
      "neighborhood": "Barceloneta",
      "tags": [
        "nature",
        "outdoor",
        "touristy",
        "wellness"
      ]
    },
    {
      "id": "bcn-shop-001",
      "city": "Barcelona",
      "country": "Spain",
      "name": "Gothic Quarter artisan lanes",
      "category": "shopping",
      "description": "Narrow streets with small shops; blend of tourist flow and hidden ateliers.",
      "lat": 41.3828,
      "lon": 2.1769,
      "neighborhood": "Gothic Quarter",
      "tags": [
        "shopping",
        "history",
        "architecture",
        "touristy"
      ]
    }
  ]
}
